lambda_rag_lite/__init__.py
lambda_rag_lite/config.py
lambda_rag_lite/constants.py
lambda_rag_lite/embeddings.py
lambda_rag_lite/factories.py
lambda_rag_lite/loaders.py
lambda_rag_lite/text_cleaning.py
lambda_rag_lite/utils.py
lambda_rag_lite/vectorstore.py
lambda_rag_lite/detectors/__init__.py
lambda_rag_lite/detectors/encoding.py
lambda_rag_lite/detectors/file_type.py
lambda_rag_lite/metadata/__init__.py
lambda_rag_lite/metadata/document_metadata.py
lambda_rag_lite/processors/__init__.py
lambda_rag_lite/processors/text_processor.py
lambda_rag_lite/strategies/__init__.py
lambda_rag_lite/strategies/chunking.py
lambda_rag_lite-0.2.0.dist-info/METADATA
lambda_rag_lite-0.2.0.dist-info/WHEEL
lambda_rag_lite-0.2.0.dist-info/licenses/LICENSE
lambda_rag_lite-0.2.0.dist-info/RECORD
