Metadata-Version: 2.4
Name: lambda-rag-lite
Version: 0.2.0
Summary: Uma biblioteca Python leve para RAG (Retrieval-Augmented Generation) compatível com LangChain, que não requer dependências pesadas como NumPy ou bibliotecas de ML.
Project-URL: Homepage, https://github.com/dmux/lambda-rag-lite
Project-URL: Repository, https://github.com/dmux/lambda-rag-lite
Project-URL: Documentation, https://github.com/dmux/lambda-rag-lite#readme
Project-URL: Issues, https://github.com/dmux/lambda-rag-lite/issues
Author-email: Rafael Sales <rafael.sales@gmail.com>
License: MIT
License-File: LICENSE
Keywords: embedding,langchain,nlp,rag,search,vector-store
Classifier: Development Status :: 3 - Alpha
Classifier: Intended Audience :: Developers
Classifier: License :: OSI Approved :: MIT License
Classifier: Programming Language :: Python :: 3
Classifier: Programming Language :: Python :: 3.10
Classifier: Programming Language :: Python :: 3.11
Classifier: Programming Language :: Python :: 3.12
Classifier: Programming Language :: Python :: 3.13
Classifier: Topic :: Scientific/Engineering :: Information Analysis
Classifier: Topic :: Software Development :: Libraries :: Python Modules
Classifier: Topic :: Text Processing :: Indexing
Requires-Python: >=3.10
Requires-Dist: langchain-core>=0.3.66
Provides-Extra: dev
Requires-Dist: black>=25.1.0; extra == 'dev'
Requires-Dist: isort>=6.0.1; extra == 'dev'
Requires-Dist: pytest-cov>=6.2.1; extra == 'dev'
Requires-Dist: pytest-mock>=3.14.1; extra == 'dev'
Requires-Dist: pytest>=8.4.1; extra == 'dev'
Requires-Dist: ruff>=0.8.0; extra == 'dev'
Provides-Extra: examples
Requires-Dist: tqdm>=4.65.0; extra == 'examples'
